keycase_agent/__init__.py
keycase_agent/agent.py
keycase_agent/auth.py
keycase_agent/config.py
keycase_agent/decorators.py
keycase_agent/event_handler.py
keycase_agent/execution_context.py
keycase_agent/execution_manager.py
keycase_agent/loader.py
keycase_agent/registry.py
keycase_agent/state_tracker.py
keycase_agent/websocket_client.py
keycase_agent/exceptions/__init__.py
keycase_agent/exceptions/auth_exceptions.py
keycase_agent/exceptions/validation_exceptions.py
keycase_agent/models/__init__.py
keycase_agent/models/execute_plan.py
keycase_agent/models/execution_result.py
keycase_agent/models/execution_run_mode_types.py
keycase_agent/models/websocket_event_types.py
keycase_agent/utils/__init__.py
keycase_agent/utils/auth_helper.py
keycase_agent/utils/event_sender.py
keycase_agent_sdk-0.1.0b2.dist-info/licenses/LICENSE
keycase_agent_sdk-0.1.0b2.dist-info/METADATA
keycase_agent_sdk-0.1.0b2.dist-info/WHEEL
keycase_agent_sdk-0.1.0b2.dist-info/entry_points.txt
keycase_agent_sdk-0.1.0b2.dist-info/top_level.txt
keycase_agent_sdk-0.1.0b2.dist-info/RECORD
