Metadata-Version: 2.4
Name: keycase-agent-sdk
Version: 0.1.0b2
Summary: Python SDK for Keycase Agent execution and keyword integration
Author: Apo
Author-email: Keycase Team <support@keycase.io>
Maintainer-email: Keycase Team <support@keycase.io>
License: MIT
Project-URL: Homepage, https://github.com/TharassKeycase/keycase-python-sdk
Project-URL: Documentation, https://docs.keycase.io/python-agent
Project-URL: Repository, https://github.com/TharassKeycase/keycase-python-sdk
Project-URL: Issues, https://github.com/TharassKeycase/keycase-python-sdk/issues
Project-URL: Changelog, https://github.com/TharassKeycase/keycase-python-sdk/blob/main/CHANGELOG.md
Keywords: automation,testing,keyword-driven,test-automation,sdk,agent
Classifier: Development Status :: 4 - Beta
Classifier: Intended Audience :: Developers
Classifier: Operating System :: OS Independent
Classifier: Programming Language :: Python :: 3
Classifier: Programming Language :: Python :: 3.8
Classifier: Programming Language :: Python :: 3.9
Classifier: Programming Language :: Python :: 3.10
Classifier: Programming Language :: Python :: 3.11
Classifier: Programming Language :: Python :: 3.12
Classifier: Topic :: Software Development :: Testing
Classifier: Topic :: Software Development :: Libraries :: Python Modules
Classifier: Typing :: Typed
Requires-Python: >=3.8
License-File: LICENSE
Requires-Dist: requests>=2.31.0
Requires-Dist: websocket-client>=1.7.0
Requires-Dist: python-dotenv>=1.0.0
Provides-Extra: dev
Requires-Dist: pytest>=7.0.0; extra == "dev"
Requires-Dist: pytest-cov>=4.0.0; extra == "dev"
Requires-Dist: pytest-asyncio>=0.21.0; extra == "dev"
Requires-Dist: pytest-mock>=3.10.0; extra == "dev"
Requires-Dist: black>=23.0.0; extra == "dev"
Requires-Dist: isort>=5.12.0; extra == "dev"
Requires-Dist: flake8>=6.0.0; extra == "dev"
Requires-Dist: mypy>=1.0.0; extra == "dev"
Requires-Dist: pre-commit>=3.0.0; extra == "dev"
Requires-Dist: types-requests>=2.31.0; extra == "dev"
Dynamic: author
Dynamic: license-file
Dynamic: requires-python
